chonf/__init__.py
chonf/core.py
chonf/exceptions.py
chonf/parsers/__init__.py
chonf/parsers/envvars/__init__.py
chonf/parsers/envvars/core.py
chonf/parsers/envvars/test/__init__.py
chonf/parsers/envvars/test/unit_test.py
chonf/parsers/json/__init__.py
chonf/parsers/json/core.py
chonf/parsers/json/test/__init__.py
chonf/parsers/json/test/unit_test.py
chonf/parsers/preprocess.py
chonf/parsers/python/__init__.py
chonf/parsers/python/core.py
chonf/parsers/python/test/__init__.py
chonf/parsers/python/test/dict_test.py
chonf/parsers/python/test/function_test.py
chonf/parsers/toml/__init__.py
chonf/parsers/toml/core.py
chonf/parsers/toml/test/__init__.py
chonf/parsers/toml/test/unit_test.py
chonf/parsers/xml/__init__.py
chonf/parsers/xml/core.py
chonf/parsers/xml/test/__init__.py
chonf/parsers/xml/test/unit_test.py
chonf/parsers/yaml/__init__.py
chonf/parsers/yaml/core.py
chonf/parsers/yaml/test/__init__.py
chonf/parsers/yaml/test/unit_test.py
chonf/paths.py
chonf/test/__init__.py
chonf/test/env_prefix_test.py
chonf/test/main_integration_test.py
chonf/test/multiple_paths_test.py
chonf/test/preprocessing_test.py
chonf/test/repeat_by_key_test.py
chonf/test/repeat_test.py
chonf/test/required_options_test.py
chonf-0.2.0.dist-info/LICENSE
chonf-0.2.0.dist-info/WHEEL
chonf-0.2.0.dist-info/METADATA
chonf-0.2.0.dist-info/RECORD
