Metadata-Version: 2.1
Name: chonf
Version: 0.2.0
Summary: User config management made simple and powerful
Home-page: https://gitlab.com/Ovenbird-j/chonf
License: Apache-2.0
Author: João C. Rodrigues Jr.
Author-email: jc.rodrigues1997@usp.br
Requires-Python: >=3.9,<4.0
Classifier: Intended Audience :: Developers
Classifier: License :: OSI Approved :: Apache Software License
Classifier: Operating System :: MacOS
Classifier: Operating System :: Microsoft :: Windows :: Windows 10
Classifier: Operating System :: Microsoft :: Windows :: Windows 7
Classifier: Operating System :: Microsoft :: Windows :: Windows 8
Classifier: Operating System :: Microsoft :: Windows :: Windows 8.1
Classifier: Operating System :: Microsoft :: Windows :: Windows Vista
Classifier: Operating System :: POSIX :: Linux
Classifier: Programming Language :: Python :: 3
Classifier: Programming Language :: Python :: 3.10
Classifier: Programming Language :: Python :: 3.9
Classifier: Topic :: Software Development :: Libraries :: Python Modules
Requires-Dist: PyYAML (>=6.0,<7.0)
Requires-Dist: toml (>=0.10.2,<0.11.0)
Requires-Dist: xmltodict (>=0.12.0,<0.13.0)
Project-URL: Bug Tracker, https://github.com/python-poetry/poetry/issues
Project-URL: Repository, https://gitlab.com/Ovenbird-j/chonf
